flux_arcane_mage/__init__.py
flux_arcane_mage/__main__.py
flux_arcane_mage/arcane_creator.tcss
flux_arcane_mage/arcane_mage.py
flux_arcane_mage/helpers.py
flux_arcane_mage/log.py
flux_arcane_mage/messages.py
flux_arcane_mage/models.py
flux_arcane_mage/password.py
flux_arcane_mage/proxmox.py
flux_arcane_mage/py.typed
flux_arcane_mage/screens/__init__.py
flux_arcane_mage/screens/confirm_screen.py
flux_arcane_mage/screens/hypervisor.py
flux_arcane_mage/screens/provision_node.py
flux_arcane_mage/screens/provisioning_info.py
flux_arcane_mage/screens/welcome.py
flux_arcane_mage/screens/welcome_proxmox.py
flux_arcane_mage/widgets/__init__.py
flux_arcane_mage/widgets/spinner.py
flux_arcane_mage-0.1.0.dist-info/METADATA
flux_arcane_mage-0.1.0.dist-info/WHEEL
flux_arcane_mage-0.1.0.dist-info/entry_points.txt
flux_arcane_mage-0.1.0.dist-info/RECORD
